[{"analysis_batch_id":"test_batch_2","analytics":{"calculated_metrics":[{"confidence_note":"These unit costs are explicitly stated by the organisation in their reporting.","confidence_tier":"HIGH","details":{"calculation":"Explicitly stated unit costs converted to USD: individual_rescue_and_sanctuary: 2000.00 RM -> $447.28","formula":"Explicitly stated unit costs by the organisation."},"id":"cost_per_outcome","name":"Cost Per Outcome (USD)","value":[{"amount":2000,"cost_usd":447.28,"currency":"RM","intervention_type":"individual_rescue_and_sanctuary","source":{"page_number":2,"quote":"Cost of $ponsorship is RM2,000 annually per kennel.","resolved_url":"https://spca-penang.net/annual_reports/annual_report_2024.pdf#page=2","source_index":0,"source_type":"attached_report"}}]},{"claimed_ies":220,"confidence_note":"IES is a Back-of-the-Envelope Calculation (BOTEC) to standardize impact across interventions and species. It relies on philosophical and empirical assumptions.","confidence_tier":"MEDIUM","details":{"breakdown":[{"calculation":"36.0 * 1 * 1 * 0.3 = 11","claimed_ies_i":36,"d_evidence":{"key":"Self-Reported","source":"Epistemic discount for 'Self-Reported' evidence.","value":0.3},"ies":11,"metric_name":"Dogs adopted","outcome":{"source_quote":"ADOPTION rate @ the Shelter is low in 2024, with Dogs & puppies (36) and Cats/Kittens (29)","value":36},"source":{"page_number":1,"quote":"ADOPTION rate @ the Shelter is low in 2024, with Dogs & puppies (36) and Cats/Kittens (29)","resolved_url":"https://spca-penang.net/annual_reports/annual_report_2024.pdf#page=1","source_index":0,"source_type":"attached_report"},"w_leverage":{"key":"individual_rescue_and_sanctuary","source":"Baseline probability for intervention 'individual_rescue_and_sanctuary'.","value":1},"w_species":{"key":"dog","source":"Moral weight for 'dog'.","value":1}},{"calculation":"29.0 * 1 * 1 * 0.3 = 9","claimed_ies_i":29,"d_evidence":{"key":"Self-Reported","source":"Epistemic discount for 'Self-Reported' evidence.","value":0.3},"ies":9,"metric_name":"Cats adopted","outcome":{"source_quote":"ADOPTION rate @ the Shelter is low in 2024, with Dogs & puppies (36) and Cats/Kittens (29)","value":29},"source":{"page_number":1,"quote":"ADOPTION rate @ the Shelter is low in 2024, with Dogs & puppies (36) and Cats/Kittens (29)","resolved_url":"https://spca-penang.net/annual_reports/annual_report_2024.pdf#page=1","source_index":0,"source_type":"attached_report"},"w_leverage":{"key":"individual_rescue_and_sanctuary","source":"Baseline probability for intervention 'individual_rescue_and_sanctuary'.","value":1},"w_species":{"key":"cat","source":"Moral weight for 'cat'.","value":1}},{"calculation":"155.0 * 1 * 1 * 0.3 = 46","claimed_ies_i":155,"d_evidence":{"key":"Self-Reported","source":"Epistemic discount for 'Self-Reported' evidence.","value":0.3},"ies":46,"metric_name":"Dogs and cats neutered and vaccinated","outcome":{"source_quote":"During the year, a total of 155 dogs and cats were neutered and vaccinated through our Neutering Fund.","value":155},"source":{"page_number":2,"quote":"During the year, a total of 155 dogs and cats were neutered and vaccinated through our Neutering Fund.","resolved_url":"https://spca-penang.net/annual_reports/annual_report_2024.pdf#page=2","source_index":0,"source_type":"attached_report"},"w_leverage":{"key":"high_volume_spay_neuter","source":"Baseline probability for intervention 'high_volume_spay_neuter'.","value":1},"w_species":{"key":"generic_companion","source":"Moral weight for 'generic_companion'.","value":1}}]},"evaluated_ies":66,"id":"impact_equivalency_score","name":"Impact Equivalency Score (IES)","value":66}],"check_items":[{"category":"Financial Health","details":{"calculation":"Required financial data is missing.","criteria":"Pass: <= 2 years of expenditure. | Warn: 2-5 years. | Fail: > 5 years.","elaboration":null,"formula":"total_reserves / total_expenditure"},"id":"check_reserve_cap","significance":"MEDIUM","status":"fail"},{"category":"Financial Health","details":{"calculation":"Required financial data is missing.","criteria":"Pass: >= 6 months of operating expenses. | Warn: 3-6 months. | Fail: < 3 months.","elaboration":null,"formula":"(current_assets - current_liabilities) / monthly_operating_expenses"},"id":"check_liquidity","significance":"MEDIUM","status":"fail"},{"category":"Impact Awareness","details":{"calculation":"Tier 2: Preventative Scale","criteria":"Pass: At least one intervention is classified as Tier 1 (Systemic Change) or Tier 2 (Prevention & Scalable Care). | Warn: All verifiable interventions are Tier 3 (Direct Care & Indirect Action).","elaboration":"[{\"tier_name\": \"Tier 2: Preventative Scale\", \"interventions\": [{\"name\": \"High Volume Spay Neuter\", \"source\": {\"source_type\": \"attached_report\", \"source_index\": 0, \"page_number\": 2, \"quote\": \"During the year, a total of 155 dogs and cats were neutered and vaccinated through our Neutering Fund.\", \"resolved_url\": \"https://spca-penang.net/annual_reports/annual_report_2024.pdf#page=2\"}}]}, {\"tier_name\": \"Tier 3: Direct Care & Indirect Action\", \"interventions\": [{\"name\": \"Individual Rescue And Sanctuary\", \"source\": {\"source_type\": \"attached_report\", \"source_index\": 0, \"page_number\": 1, \"quote\": \"ADOPTION rate @ the Shelter is low in 2024, with Dogs & puppies (36) and Cats/Kittens (29)\", \"resolved_url\": \"https://spca-penang.net/annual_reports/annual_report_2024.pdf#page=1\"}}, {\"name\": \"Individual Rescue And Sanctuary\", \"source\": {\"source_type\": \"attached_report\", \"source_index\": 0, \"page_number\": 1, \"quote\": \"ADOPTION rate @ the Shelter is low in 2024, with Dogs & puppies (36) and Cats/Kittens (29)\", \"resolved_url\": \"https://spca-penang.net/annual_reports/annual_report_2024.pdf#page=1\"}}]}]","formula":"Mapping of verified intervention types to the Intervention Leverage Tier framework."},"id":"check_intervention_tractability","significance":"HIGH","status":"pass"},{"category":"Impact Awareness","details":{"calculation":"A quantified counterfactual baseline was provided.","criteria":"Pass: At least one metric has a quantified counterfactual baseline. | Warn: A qualitative baseline is provided, but lacks quantified data. | Fail: No valid counterfactual baseline is provided.","elaboration":"Quote: 'ADOPTION rate @ the Shelter is low in 2024, with Dogs & puppies (36) and Cats/Kittens (29)'","formula":"Presence of a quantified counterfactual baseline with a source quote."},"id":"check_counterfactual_baseline","significance":"MEDIUM","status":"pass"},{"category":"Impact Awareness","details":{"calculation":"Financials with income breakdown are missing.","criteria":"Pass: Government grants are < 80% of total income. | Fail: Government grants are >= 80% of total income.","elaboration":null,"formula":"government_grants / total_income"},"id":"check_funding_neglectedness","significance":"MEDIUM","status":"warning"},{"category":"Impact Awareness","details":{"calculation":"Operates in a low-neglectedness / saturated area (Companion Animals: 100%).","criteria":"Pass: >= 50% of beneficiaries are high-neglectedness (farmed/wild). | Warn: 1-49% are high-neglectedness. | Fail: 0% are high-neglectedness.","elaboration":null,"formula":"Proportional analysis of beneficiary populations (farmed/wild vs. companion)"},"id":"check_cause_area_neglectedness","significance":"HIGH","status":"fail"},{"category":"Transparency","details":{"calculation":"Organisation self-reported on unintended negative impacts.","criteria":"Bonus: Organisation self-reported on unintended negative impacts. | Not Disclosed: No disclosure found.","elaboration":"Quote: 'ADOPTION rate @ the Shelter is low in 2024, with Dogs & puppies (36) and Cats/Kittens (29)\nThe continuing Low Rate with each passing year is partly contributed by:\nA) TIGHT BUDGET - faced by the public due to Inflation and High Cost of Living.\n(# Unfortunately, not everyone is keen to release them back to its environment, which leaves SPCA\nno option but to release them in areas where there is \"food Source\"'","formula":"Check for self-reported unintended consequences or failures."},"id":"check_negative_impact_disclosure","significance":"MEDIUM","status":"bonus"},{"category":"Transparency","details":{"calculation":"No disclosure of euthanasia or live-release rates found.","criteria":"Bonus: Euthanasia/live-release data is disclosed. | Not Disclosed: No disclosure found. | N/A: Not applicable for non-sheltering organisations.","elaboration":"This check rewards transparency for a sensitive operational metric.","formula":"For direct rescue orgs, check for euthanasia/live-release rate disclosure."},"id":"check_live_release_transparency","significance":"HIGH","status":"not_disclosed"}]},"annual_report":"az4hzx43ek4wsvz","collectionId":"pbc_1763078910","collectionName":"organisations","created":"2026-04-21 16:00:13.489Z","expand":{"annual_report":{"collectionId":"pbc_2034649627","collectionName":"source_artifacts","created":"2026-04-22 09:36:43.060Z","gemini_file_uploaded":"2026-04-22 09:36:51.795Z","gemini_file_uri":"https://generativelanguage.googleapis.com/v1beta/files/enzfj75udbtb","id":"az4hzx43ek4wsvz","raw":"annual_report_2024_n2xpagpg4r.pdf","text":"file_355i4662i5.txt","updated":"2026-04-22 09:36:51.805Z","url":"https://spca-penang.net/annual_reports/annual_report_2024.pdf"}},"financial_report":"","financials":{"data":{"currency":{"original_code":"MYR","rate_date":"2024-12-31","usd_exchange_rate":0.22364},"expenditure":{"administration":{"scale_multiplier":1,"source":null,"value":null},"fundraising":{"scale_multiplier":1,"source":null,"value":null},"program_breakdowns":[],"program_services":{"scale_multiplier":1,"source":null,"value":null},"total":{"scale_multiplier":1,"source":null,"value":null}},"financial_year":"2024","income":{"donations":{"scale_multiplier":1,"source":{"page_number":2,"quote":"COLLECTION BOXES ... in which we collected a Total sum of RM 12,645.55 for 2024. Our Sincere appreciation for your continued and kind support. Thank you. ... APPENDIX A - List of Donations 2024","resolved_url":"https://spca-penang.net/annual_reports/annual_report_2024.pdf#page=2","source_index":0,"source_type":"attached_report"},"value":213139},"government_grants":{"scale_multiplier":1,"source":null,"value":null},"total":{"scale_multiplier":1,"source":{"page_number":2,"quote":"COLLECTION BOXES ... in which we collected a Total sum of RM 12,645.55 for 2024. Our Sincere appreciation for your continued and kind support. Thank you. ... APPENDIX A - List of Donations 2024","resolved_url":"https://spca-penang.net/annual_reports/annual_report_2024.pdf#page=2","source_index":0,"source_type":"attached_report"},"value":213139}},"lsg_specifics":{"lsg_reserve_amount":{"scale_multiplier":1,"source":null,"value":null},"provident_fund_reserve":{"scale_multiplier":1,"source":null,"value":null}},"ratio_inputs":{"current_assets":{"scale_multiplier":1,"source":null,"value":null},"current_liabilities":{"scale_multiplier":1,"source":null,"value":null},"monthly_operating_expenses":{"scale_multiplier":1,"source":null,"value":null},"net_current_assets":{"scale_multiplier":1,"source":null,"value":null}},"reserves":{"total_reserves":{"scale_multiplier":1,"source":null,"value":null}}},"schema":{"schema":"v1/financials.schema.json","valid":true}},"gemini_cache_name":"cachedContents/13gc6j3jf6bkp5bg7znek5gwrj550xsfda6b0m7e","gemini_cached":"2026-04-23 11:10:24.859Z","id":"ze7m3v932adcqon","impact":{"data":{"beneficiaries":{"beneficiaries":[{"beneficiary_type":"companion_animals","location":"the Shelter","population":36,"source":{"page_number":1,"quote":"ADOPTION rate @ the Shelter is low in 2024, with Dogs & puppies (36) and Cats/Kittens (29)","resolved_url":"https://spca-penang.net/annual_reports/annual_report_2024.pdf#page=1","source_index":0,"source_type":"attached_report"}},{"beneficiary_type":"companion_animals","location":"the Shelter","population":29,"source":{"page_number":1,"quote":"ADOPTION rate @ the Shelter is low in 2024, with Dogs & puppies (36) and Cats/Kittens (29)","resolved_url":"https://spca-penang.net/annual_reports/annual_report_2024.pdf#page=1","source_index":0,"source_type":"attached_report"}},{"beneficiary_type":"companion_animals","location":"local community","population":155,"source":{"page_number":2,"quote":"During the year, a total of 155 dogs and cats were neutered and vaccinated through our Neutering Fund.","resolved_url":"https://spca-penang.net/annual_reports/annual_report_2024.pdf#page=2","source_index":0,"source_type":"attached_report"}}]},"interventions":{"context":{"explicit_unit_costs":[{"amount":2000,"currency":"RM","description":"annually per kennel","intervention_type":"individual_rescue_and_sanctuary","source":{"page_number":2,"quote":"Cost of $ponsorship is RM2,000 annually per kennel.","resolved_url":"https://spca-penang.net/annual_reports/annual_report_2024.pdf#page=2","source_index":0,"source_type":"attached_report"}}],"operating_scope":{"source":{"page_number":1,"quote":"The year 2024 have been a busy year for the Society, as we try hard to meet the Mission of the Society ie.to protect and improve on the welfare of animals.","resolved_url":"https://spca-penang.net/annual_reports/annual_report_2024.pdf#page=1","source_index":0,"source_type":"attached_report"},"value":"pure_animal_advocacy"}}},"metrics":{"metrics":[{"context_qualifier":"from the Shelter","counterfactual_baseline":{"source":{"page_number":1,"quote":"ADOPTION rate @ the Shelter is low in 2024, with Dogs & puppies (36) and Cats/Kittens (29)","resolved_url":"https://spca-penang.net/annual_reports/annual_report_2024.pdf#page=1","source_index":0,"source_type":"attached_report"},"value":0},"evidence_quality":"Self-Reported","intervention_key":"individual_rescue_and_sanctuary","metric_name":"Dogs adopted","quantitative_data":{"unit":"dogs","unit_is_individual_animal":true,"value":36},"source":{"page_number":1,"quote":"ADOPTION rate @ the Shelter is low in 2024, with Dogs & puppies (36) and Cats/Kittens (29)","resolved_url":"https://spca-penang.net/annual_reports/annual_report_2024.pdf#page=1","source_index":0,"source_type":"attached_report"},"species_key":"dog","timeframe":"annual"},{"context_qualifier":"from the Shelter","counterfactual_baseline":{"source":{"page_number":1,"quote":"ADOPTION rate @ the Shelter is low in 2024, with Dogs & puppies (36) and Cats/Kittens (29)","resolved_url":"https://spca-penang.net/annual_reports/annual_report_2024.pdf#page=1","source_index":0,"source_type":"attached_report"},"value":0},"evidence_quality":"Self-Reported","intervention_key":"individual_rescue_and_sanctuary","metric_name":"Cats adopted","quantitative_data":{"unit":"cats","unit_is_individual_animal":true,"value":29},"source":{"page_number":1,"quote":"ADOPTION rate @ the Shelter is low in 2024, with Dogs & puppies (36) and Cats/Kittens (29)","resolved_url":"https://spca-penang.net/annual_reports/annual_report_2024.pdf#page=1","source_index":0,"source_type":"attached_report"},"species_key":"cat","timeframe":"annual"},{"context_qualifier":"through our Neutering Fund","counterfactual_baseline":{"source":{"page_number":2,"quote":"During the year, a total of 155 dogs and cats were neutered and vaccinated through our Neutering Fund.","resolved_url":"https://spca-penang.net/annual_reports/annual_report_2024.pdf#page=2","source_index":0,"source_type":"attached_report"},"value":0},"evidence_quality":"Self-Reported","intervention_key":"high_volume_spay_neuter","metric_name":"Dogs and cats neutered and vaccinated","quantitative_data":{"unit":"animals","unit_is_individual_animal":true,"value":155},"source":{"page_number":2,"quote":"During the year, a total of 155 dogs and cats were neutered and vaccinated through our Neutering Fund.","resolved_url":"https://spca-penang.net/annual_reports/annual_report_2024.pdf#page=2","source_index":0,"source_type":"attached_report"},"species_key":"generic_companion","timeframe":"annual"}]},"transparency":{"transparency_indicators":{"euthanasia_statistics_reported":{"source":{"page_number":1,"quote":"The year 2024 have been a busy year for the Society, as we try hard to meet the Mission of the\nSociety ie.to protect and improve on the welfare of animals.\nWe work this goal by:\nProviding Shelter & Food\nGiving Medical Care & attention to animals in need\nAdvocating for better animal welfare laws & enforcement\nEducating the public about the importance of respecting animals; AND ensuring they live\nhealthy, happy & dignified -free from pain & suffering. Or at least given proper treatment,\ncare & love to minimize their discomfort & suffering.","resolved_url":"https://spca-penang.net/annual_reports/annual_report_2024.pdf#page=1","source_index":0,"source_type":"attached_report"},"value":false},"unintended_consequences_reported":{"source":{"page_number":1,"quote":"ADOPTION rate @ the Shelter is low in 2024, with Dogs & puppies (36) and Cats/Kittens (29)\nThe continuing Low Rate with each passing year is partly contributed by:\nA) TIGHT BUDGET - faced by the public due to Inflation and High Cost of Living.\n(# Unfortunately, not everyone is keen to release them back to its environment, which leaves SPCA\nno option but to release them in areas where there is \"food Source\"","resolved_url":"https://spca-penang.net/annual_reports/annual_report_2024.pdf#page=1","source_index":0,"source_type":"attached_report"},"value":true}}}},"schema":{"beneficiaries":{"schema":"v1/impact_beneficiaries.schema.json","valid":true},"interventions":{"schema":"v1/impact_interventions.schema.json","valid":true},"metrics":{"schema":"v1/impact_metrics.schema.json","valid":true},"transparency":{"schema":"v1/impact_transparency.schema.json","valid":true}}},"meta":{"aliases":["RSPCA","SPCA","Society for the Prevention of Cruelty to Animals"],"chinese_name":null,"domains":["www.spca-penang.net"],"registration_id":"PPM-004-07-22031950"},"name":"SPCA Penang","updated":"2026-04-23 13:07:33.327Z"}]